reb/__init__.py
reb/cli.py
reb/exceptions.py
reb/parse_tree.py
reb/pattern.py
reb/plain.py
reb/to_re.py
reb/vm.py
reb-0.1.0.dist-info/LICENSE
reb-0.1.0.dist-info/METADATA
reb-0.1.0.dist-info/WHEEL
reb-0.1.0.dist-info/entry_points.txt
reb-0.1.0.dist-info/top_level.txt
reb-0.1.0.dist-info/RECORD
