Metadata-Version: 2.1
Name: reb
Version: 0.1.0
Summary: Regular Expression Beautiful
Home-page: https://github.com/workingenius/reb
Author: ruqishang
Author-email: workingenius@163.com
License: MIT
Platform: UNKNOWN
Provides-Extra: dev
Requires-Dist: pytest ; extra == 'dev'
Requires-Dist: mypy ; extra == 'dev'
